{"tags": ["aid effectiveness", "hxl", "indicators", "Saint Kitts And Nevis"], "downloads": 61, "title": "St. Kitts and Nevis - Aid Effectiveness", "hxl": 1, "org": "World Bank Group", "id": "3f52824c-51c2-477c-a260-6c27ae6a60bb", "resources": [{"link": "https://data.humdata.org/dataset/3f52824c-51c2-477c-a260-6c27ae6a60bb/resource/12b05a37-0401-4977-a951-f7448e680493/download/aid-effectiveness_kna.csv", "update_date": "2021-01-28T12:11:57.766108", "bites": {"maps": {"bites": []}, "charts": {"bites": [{"title": "Value by Indicator Name for 2019", "bite": [["Indicator Name", "Value"], ["Mortality rate, under-5 (per 1,000 live births)", 15.4], ["Incidence of tuberculosis (per 100,000 people)", 1.5]], "priority": 8, "subtype": "row", "uniqueID": "chart0007/#indicator+name/3/#indicator+num+value/5/timefilter", "type": "chart", "id": "chart0007"}, {"title": "Value by Indicator Code for 2019", "bite": [["Indicator Code", "Value"], ["SH.DYN.MORT", 15.4], ["SH.TBS.INCD", 1.5]], "priority": 8, "subtype": "row", "uniqueID": "chart0007/#indicator+code/4/#indicator+num+value/5/timefilter", "type": "chart", "id": "chart0007"}, {"title": "Top 10 of Value by Indicator Name", "bite": [["Indicator Name", "Value"], ["Net official development assistance and official aid received (constant 2015 US$)", 448890003.29747814], ["Net official development assistance received (constant 2015 US$)", 448890003.29747814], ["Net official development assistance and official aid received (current US$)", 330859998.8464265], ["Net official development assistance received (current US$)", 330859998.8464265], ["Net bilateral aid flows from DAC donors, Total (current US$)", 219969999.2872774], ["Grants, excluding technical cooperation (BoP, current US$)", 196850000], ["Net bilateral aid flows from DAC donors, European Union institutions (current US$)", 89410000.2516061], ["Technical cooperation grants (BoP, current US$)", 51510000], ["Net bilateral aid flows from DAC donors, United Kingdom (current US$)", 41030000.17255547], ["Net bilateral aid flows from DAC donors, Italy (current US$)", 33599998.777732275]], "priority": 8, "subtype": "row", "uniqueID": "chart0014/#indicator+name/3/#indicator+num+value/5", "type": "chart", "id": "chart0014"}, {"title": "Top 10 of Value by Indicator Code", "bite": [["Indicator Code", "Value"], ["DT.ODA.ALLD.KD", 448890003.29747814], ["DT.ODA.ODAT.KD", 448890003.29747814], ["DT.ODA.ALLD.CD", 330859998.8464265], ["DT.ODA.ODAT.CD", 330859998.8464265], ["DC.DAC.TOTL.CD", 219969999.2872774], ["BX.GRT.EXTA.CD.WD", 196850000], ["DC.DAC.CECL.CD", 89410000.2516061], ["BX.GRT.TECH.CD.WD", 51510000], ["DC.DAC.GBRL.CD", 41030000.17255547], ["DC.DAC.ITAL.CD", 33599998.777732275]], "priority": 8, "subtype": "row", "uniqueID": "chart0014/#indicator+code/4/#indicator+num+value/5", "type": "chart", "id": "chart0014"}]}, "text": {"bites": [{"priority": 10, "subtype": "datefilter", "bite": "Data filtered on Year for 2019", "type": "text", "id": "text0000"}, {"bite": "<span class=\"hbheader\">Value</span>: <span class=\"hbvalue\">16.9</span>", "priority": 8, "subtype": "topline figure", "uniqueID": "text0017/#indicator+num+value/5/timefilter", "type": "text", "id": "text0017"}, {"priority": 10, "subtype": "datefilter", "bite": "Data filtered on Year for 2019", "type": "text", "id": "text0000"}, {"bite": "<span class=\"hbheader\">Value</span>: <span class=\"hbvalue\">2264021800.8108478</span>", "priority": 8, "subtype": "topline figure", "uniqueID": "text0017/#indicator+num+value/5", "type": "text", "id": "text0017"}]}}, "hxl": 1}, {"link": "https://data.humdata.org/dataset/3f52824c-51c2-477c-a260-6c27ae6a60bb/resource/6be9eb32-1c94-4f03-ab77-56dbd2d9e9c1/download/qc_aid-effectiveness_kna.csv", "update_date": "2021-01-28T12:11:57.766108", "bites": {"maps": {"bites": []}, "charts": {"bites": [{"title": "Value by Indicator Code for 2019", "bite": [["Indicator Code", "Value"], ["SH.DYN.MORT", 15.4], ["SH.TBS.INCD", 1.5]], "priority": 8, "subtype": "row", "uniqueID": "chart0007/#indicator+code/2/#indicator+num+value/3/timefilter", "type": "chart", "id": "chart0007"}, {"title": "Value by Indicator Code", "bite": [["Indicator Code", "Value"], ["SH.DYN.MORT", 1524.3999999999999], ["SH.TBS.INCD", 89.2], ["DC.DAC.AUSL.CD", 1909999.96103346]], "priority": 8, "subtype": "row", "uniqueID": "chart0007/#indicator+code/2/#indicator+num+value/3", "type": "chart", "id": "chart0007"}]}, "text": {"bites": [{"priority": 10, "subtype": "datefilter", "bite": "Data filtered on Year for 2019", "type": "text", "id": "text0000"}, {"bite": "<span class=\"hbheader\">Value</span>: <span class=\"hbvalue\">16.9</span>", "priority": 8, "subtype": "topline figure", "uniqueID": "text0017/#indicator+num+value/3/timefilter", "type": "text", "id": "text0017"}, {"priority": 10, "subtype": "datefilter", "bite": "Data filtered on Year for 2019", "type": "text", "id": "text0000"}, {"bite": "<span class=\"hbheader\">Value</span>: <span class=\"hbvalue\">1911613.5610334603</span>", "priority": 8, "subtype": "topline figure", "uniqueID": "text0017/#indicator+num+value/3", "type": "text", "id": "text0017"}]}}, "hxl": 1}]}