{"title": "Mauritania - Economic, Social, Environmental, Health, Education, Development and Energy", "downloads": 234, "tags": ["agriculture", "aid effectiveness", "development", "economics", "education", "energy", "environment", "facilities and infrastructure", "gender", "health", "hxl", "indicators", "international trade", "millennium development goals - mdg", "mining", "poverty", "socioeconomics", "weather and climate", "Mauritania"], "hxl": 1, "org": "World Bank Group", "id": "4948a902-162e-4986-9859-7b1509a02ef3", "resources": [{"bites": {"maps": {"bites": []}, "charts": {"bites": [{"title": "Top 10 of Value by Indicator Name for 2020", "bite": [["Indicator Name", "Value"], ["Labor force, total", 2574654], ["School age population, primary education, both sexes (number)", 693675], ["School age population, secondary education, both sexes (number)", 676504], ["Labor force, female", 406553], ["School age population, lower secondary education, both sexes (number)", 401580], ["School age population, primary education, male (number)", 351933], ["School age population, secondary education, male (number)", 342865], ["School age population, primary education, female (number)", 341742], ["School age population, secondary education, female (number)", 333639], ["School age population, upper secondary education, both sexes (number)", 274924]], "priority": 8, "subtype": "row", "uniqueID": "chart0014/#indicator+name/3/#indicator+num+value/5/timefilter", "type": "chart", "id": "chart0014"}, {"title": "Top 10 of Value by Indicator Code for 2020", "bite": [["Indicator Code", "Value"], ["SL.TLF.TOTL.IN", 2574654], ["SP.PRM.TOTL.IN", 693675], ["SP.SEC.TOTL.IN", 676504], ["SL.TLF.TOTL.FE.IN", 406553], ["SP.SEC.LTOT.IN", 401580], ["SP.PRM.TOTL.MA.IN", 351933], ["SP.SEC.TOTL.MA.IN", 342865], ["SP.PRM.TOTL.FE.IN", 341742], ["SP.SEC.TOTL.FE.IN", 333639], ["SP.SEC.UTOT.IN", 274924]], "priority": 8, "subtype": "row", "uniqueID": "chart0014/#indicator+code/4/#indicator+num+value/5/timefilter", "type": "chart", "id": "chart0014"}, {"title": "Top 10 of Value by Indicator Name", "bite": [["Indicator Name", "Value"], ["Gross national income (constant LCU)", 18200234231786.87], ["Gross national expenditure (constant LCU)", 6732020770868.729], ["Gross value added at basic prices (GVA) (constant LCU)", 6653577724062.325], ["GDP (constant LCU)", 6552556270890.498], ["GNI (constant LCU)", 6118155451953.638], ["Gross domestic income (constant LCU)", 5988925067585.377], ["Final consumption expenditure (constant LCU)", 5065695138263.544], ["Exports as a capacity to import (constant LCU)", 4183604431305.1035], ["Gross national expenditure (current LCU)", 3726573721250.6133], ["Households and NPISHs Final consumption expenditure (constant LCU)", 3681976860080.4214]], "priority": 8, "subtype": "row", "uniqueID": "chart0014/#indicator+name/3/#indicator+num+value/5", "type": "chart", "id": "chart0014"}, {"title": "Top 10 of Value by Indicator Code", "bite": [["Indicator Code", "Value"], ["NY.GNY.TOTL.KN", 18200234231786.87], ["NE.DAB.TOTL.KN", 6732020770868.729], ["NY.GDP.FCST.KN", 6653577724062.325], ["NY.GDP.MKTP.KN", 6552556270890.498], ["NY.GNP.MKTP.KN", 6118155451953.638], ["NY.GDY.TOTL.KN", 5988925067585.377], ["NE.CON.TOTL.KN", 5065695138263.544], ["NY.EXP.CAPM.KN", 4183604431305.1035], ["NE.DAB.TOTL.CN", 3726573721250.6133], ["NE.CON.PRVT.KN", 3681976860080.4214]], "priority": 8, "subtype": "row", "uniqueID": "chart0014/#indicator+code/4/#indicator+num+value/5", "type": "chart", "id": "chart0014"}]}, "text": {"bites": [{"priority": 10, "subtype": "datefilter", "bite": "Data filtered on Year for 2020", "type": "text", "id": "text0000"}, {"bite": "<span class=\"hbheader\">Value</span>: <span class=\"hbvalue\">7540765.838146205</span>", "priority": 8, "subtype": "topline figure", "uniqueID": "text0017/#indicator+num+value/5/timefilter", "type": "text", "id": "text0017"}, {"priority": 10, "subtype": "datefilter", "bite": "Data filtered on Year for 2020", "type": "text", "id": "text0000"}, {"bite": "<span class=\"hbheader\">Value</span>: <span class=\"hbvalue\">120885887414463.78</span>", "priority": 8, "subtype": "topline figure", "uniqueID": "text0017/#indicator+num+value/5", "type": "text", "id": "text0017"}]}}, "update_date": "2021-01-29T04:18:53.543039", "link": "https://data.humdata.org/dataset/4948a902-162e-4986-9859-7b1509a02ef3/resource/605eb8cc-b814-416d-a4c9-b79ec092b3bc/download/indicators_mrt.csv", "hxl": 1}, {"bites": {"maps": {"bites": []}, "charts": {"bites": [{"title": "Value by Indicator Code for 2019", "bite": [["Indicator Code", "Value"], ["SP.POP.TOTL", 9051392], ["SE.PRM.ENRR", 100.408630371094]], "priority": 8, "subtype": "row", "uniqueID": "chart0007/#indicator+code/2/#indicator+num+value/3/timefilter", "type": "chart", "id": "chart0007"}, {"title": "Value by Indicator Code", "bite": [["Indicator Code", "Value"], ["SP.POP.TOTL", 266569414], ["SP.DYN.LE00.IN", 3359.178], ["SE.PRM.ENRR", 3165.3688516616826]], "priority": 8, "subtype": "row", "uniqueID": "chart0007/#indicator+code/2/#indicator+num+value/3", "type": "chart", "id": "chart0007"}]}, "text": {"bites": [{"priority": 10, "subtype": "datefilter", "bite": "Data filtered on Year for 2019", "type": "text", "id": "text0000"}, {"bite": "<span class=\"hbheader\">Value</span>: <span class=\"hbvalue\">9051492.408630371</span>", "priority": 8, "subtype": "topline figure", "uniqueID": "text0017/#indicator+num+value/3/timefilter", "type": "text", "id": "text0017"}, {"priority": 10, "subtype": "datefilter", "bite": "Data filtered on Year for 2019", "type": "text", "id": "text0000"}, {"bite": "<span class=\"hbheader\">Value</span>: <span class=\"hbvalue\">266575938.54685166</span>", "priority": 8, "subtype": "topline figure", "uniqueID": "text0017/#indicator+num+value/3", "type": "text", "id": "text0017"}]}}, "update_date": "2021-01-29T04:18:53.543039", "link": "https://data.humdata.org/dataset/4948a902-162e-4986-9859-7b1509a02ef3/resource/23f69f2b-82c3-4229-8d17-db15c4565165/download/qc_indicators_mrt.csv", "hxl": 1}]}