{"title": "Japan - Education", "downloads": 86, "tags": ["education", "hxl", "indicators", "Japan"], "hxl": 1, "org": "World Bank Group", "id": "68872b20-24d7-48cb-9d3b-4b80d1d36479", "resources": [{"bites": {"maps": {"bites": []}, "charts": {"bites": [{"title": "Top 10 of Value by Indicator Name for 2020", "bite": [["Indicator Name", "Value"], ["Labor force, total", 67802081], ["Labor force, female (% of total labor force)", 44.1074810078469], ["Official entrance age to upper secondary education (years)", 15], ["Lower secondary school starting age (years)", 12], ["Primary school starting age (years)", 6], ["Primary education, duration (years)", 6], ["Secondary education, duration (years)", 6], ["Theoretical duration of lower secondary education (years)", 3], ["Theoretical duration of upper secondary education (years)", 3], ["Unemployment, male (% of male labor force) (modeled ILO estimate)", 2.42600011825562]], "priority": 8, "subtype": "row", "uniqueID": "chart0014/#indicator+name/3/#indicator+num+value/5/timefilter", "type": "chart", "id": "chart0014"}, {"title": "Top 10 of Value by Indicator Code for 2020", "bite": [["Indicator Code", "Value"], ["SL.TLF.TOTL.IN", 67802081], ["SL.TLF.TOTL.FE.ZS", 44.1074810078469], ["UIS.THAGE.3.A.GPV", 15], ["SE.SEC.AGES", 12], ["SE.PRM.AGES", 6], ["SE.PRM.DURS", 6], ["SE.SEC.DURS", 6], ["SE.SEC.DURS.LO", 3], ["SE.SEC.DURS.UP", 3], ["SL.UEM.TOTL.MA.ZS", 2.42600011825562]], "priority": 8, "subtype": "row", "uniqueID": "chart0014/#indicator+code/4/#indicator+num+value/5/timefilter", "type": "chart", "id": "chart0014"}, {"title": "Top 10 of Value by Indicator Name", "bite": [["Indicator Name", "Value"], ["Labor force, total", 2071686538], ["Primary education, pupils", 424526546], ["Secondary education, pupils", 419260067], ["Population, ages 15-24, total", 399822196], ["Population, ages 10-18, total", 324676179], ["Population, ages 11-18, total", 291277113], ["Population, ages 10-17, total", 285618116], ["Population, ages 13-19, total", 262647958], ["Population, ages 12-18, total", 257375697], ["Population, ages 11-17, total", 252219050]], "priority": 8, "subtype": "row", "uniqueID": "chart0014/#indicator+name/3/#indicator+num+value/5", "type": "chart", "id": "chart0014"}, {"title": "Top 10 of Value by Indicator Code", "bite": [["Indicator Code", "Value"], ["SL.TLF.TOTL.IN", 2071686538], ["SE.PRM.ENRL", 424526546], ["SE.SEC.ENRL", 419260067], ["SP.POP.1524.TO.UN", 399822196], ["SP.POP.1018.TO.UN", 324676179], ["SP.POP.1118.TO.UN", 291277113], ["SP.POP.1017.TO.UN", 285618116], ["SP.POP.1319.TO.UN", 262647958], ["SP.POP.1218.TO.UN", 257375697], ["SP.POP.1117.TO.UN", 252219050]], "priority": 8, "subtype": "row", "uniqueID": "chart0014/#indicator+code/4/#indicator+num+value/5", "type": "chart", "id": "chart0014"}]}, "text": {"bites": [{"priority": 10, "subtype": "datefilter", "bite": "Data filtered on Year for 2020", "type": "text", "id": "text0000"}, {"bite": "<span class=\"hbheader\">Value</span>: <span class=\"hbvalue\">67802183.10048103</span>", "priority": 8, "subtype": "topline figure", "uniqueID": "text0017/#indicator+num+value/5/timefilter", "type": "text", "id": "text0017"}, {"priority": 10, "subtype": "datefilter", "bite": "Data filtered on Year for 2020", "type": "text", "id": "text0000"}, {"bite": "<span class=\"hbheader\">Value</span>: <span class=\"hbvalue\">19846094965.69568</span>", "priority": 8, "subtype": "topline figure", "uniqueID": "text0017/#indicator+num+value/5", "type": "text", "id": "text0017"}]}}, "update_date": "2021-01-28T11:30:38.849460", "link": "https://data.humdata.org/dataset/68872b20-24d7-48cb-9d3b-4b80d1d36479/resource/ff89f798-bf59-440a-b63a-d3397ab8be73/download/education_jpn.csv", "hxl": 1}, {"bites": {"maps": {"bites": []}, "charts": {"bites": [{"title": "Value by Indicator Code", "bite": [["Indicator Code", "Value"], ["UIS.E.2", 88742575], ["UIS.E.3", 93478539], ["UIS.E.4", 297603]], "priority": 8, "subtype": "row", "uniqueID": "chart0007/#indicator+code/2/#indicator+num+value/3", "type": "chart", "id": "chart0007"}]}, "text": {"bites": [{"bite": "<span class=\"hbheader\">Value</span>: <span class=\"hbvalue\">182518717</span>", "priority": 8, "subtype": "topline figure", "uniqueID": "text0017/#indicator+num+value/3", "type": "text", "id": "text0017"}]}}, "update_date": "2021-01-28T11:30:38.849460", "link": "https://data.humdata.org/dataset/68872b20-24d7-48cb-9d3b-4b80d1d36479/resource/3fd4a3d2-5907-439b-82d0-83d118741055/download/qc_education_jpn.csv", "hxl": 1}]}