{"tags": ["facilities and infrastructure", "hxl", "indicators", "Cabo Verde"], "downloads": 85, "title": "Cabo Verde - Infrastructure", "hxl": 1, "org": "World Bank Group", "id": "b77b8495-58f6-421a-99af-9215556aca58", "resources": [{"link": "https://data.humdata.org/dataset/b77b8495-58f6-421a-99af-9215556aca58/resource/9eecca9a-6f5e-48b3-9deb-a754365e39c9/download/infrastructure_cpv.csv", "update_date": "2021-01-28T05:10:56.400331", "bites": {"maps": {"bites": []}, "charts": {"bites": [{"title": "Value by Indicator Name for 2020", "bite": [["Indicator Name", "Value"], ["Secure Internet servers", 99], ["Secure Internet servers (per 1 million people)", 178.057553956835]], "priority": 8, "subtype": "row", "uniqueID": "chart0007/#indicator+name/3/#indicator+num+value/5/timefilter", "type": "chart", "id": "chart0007"}, {"title": "Value by Indicator Code for 2020", "bite": [["Indicator Code", "Value"], ["IT.NET.SECR", 99], ["IT.NET.SECR.P6", 178.057553956835]], "priority": 8, "subtype": "row", "uniqueID": "chart0007/#indicator+code/4/#indicator+num+value/5/timefilter", "type": "chart", "id": "chart0007"}, {"title": "Top 10 of Value by Indicator Name", "bite": [["Indicator Name", "Value"], ["Revenue from all telecommunication services (current LCU)", 89105043628], ["Annual investment in telecommunications (current LCU)", 20328210959], ["ICT service exports (BoP, current US$)", 490286829.2758672], ["Investment in energy with private participation (current US$)", 80000000], ["Public private partnerships investment in energy (current US$)", 80000000], ["Air transport, passengers carried", 14184260.35149216], ["Mobile cellular subscriptions", 6471635], ["Mobile and fixed-line telephone subscribers", 3004120.1], ["Fixed telephone subscriptions", 1620402.1], ["Container port traffic (TEU: 20 foot equivalent units)", 493894.3599999999]], "priority": 8, "subtype": "row", "uniqueID": "chart0014/#indicator+name/3/#indicator+num+value/5", "type": "chart", "id": "chart0014"}, {"title": "Top 10 of Value by Indicator Code", "bite": [["Indicator Code", "Value"], ["IT.TEL.REVN.CN", 89105043628], ["IT.TEL.INVS.CN", 20328210959], ["BX.GSR.CCIS.CD", 490286829.2758672], ["IE.PPI.ENGY.CD", 80000000], ["IE.PPN.ENGY.CD", 80000000], ["IS.AIR.PSGR", 14184260.35149216], ["IT.CEL.SETS", 6471635], ["IT.TEL.TOTL", 3004120.1], ["IT.MLT.MAIN", 1620402.1], ["IS.SHP.GOOD.TU", 493894.3599999999]], "priority": 8, "subtype": "row", "uniqueID": "chart0014/#indicator+code/4/#indicator+num+value/5", "type": "chart", "id": "chart0014"}]}, "text": {"bites": [{"priority": 10, "subtype": "datefilter", "bite": "Data filtered on Year for 2020", "type": "text", "id": "text0000"}, {"bite": "<span class=\"hbheader\">Value</span>: <span class=\"hbvalue\">277.057553956835</span>", "priority": 8, "subtype": "topline figure", "uniqueID": "text0017/#indicator+num+value/5/timefilter", "type": "text", "id": "text0017"}, {"priority": 10, "subtype": "datefilter", "bite": "Data filtered on Year for 2020", "type": "text", "id": "text0000"}, {"bite": "<span class=\"hbheader\">Value</span>: <span class=\"hbvalue\">110109942137.45438</span>", "priority": 8, "subtype": "topline figure", "uniqueID": "text0017/#indicator+num+value/5", "type": "text", "id": "text0017"}]}}, "hxl": 1}, {"link": "https://data.humdata.org/dataset/b77b8495-58f6-421a-99af-9215556aca58/resource/77bef9f9-14eb-47e7-9587-cdd0928bea69/download/qc_infrastructure_cpv.csv", "update_date": "2021-01-28T05:10:56.400331", "bites": {"maps": {"bites": []}, "charts": {"bites": [{"title": "Value by Indicator Code for 2019", "bite": [["Indicator Code", "Value"], ["IP.TMK.NRCT", 193], ["IP.TMK.RSCT", 91], ["IS.AIR.DPRT", 10205]], "priority": 8, "subtype": "row", "uniqueID": "chart0007/#indicator+code/2/#indicator+num+value/3/timefilter", "type": "chart", "id": "chart0007"}, {"title": "Value by Indicator Code", "bite": [["Indicator Code", "Value"], ["IS.AIR.DPRT", 383529.2999446842], ["IP.TMK.NRCT", 820], ["IP.TMK.RSCT", 407]], "priority": 8, "subtype": "row", "uniqueID": "chart0007/#indicator+code/2/#indicator+num+value/3", "type": "chart", "id": "chart0007"}]}, "text": {"bites": [{"priority": 10, "subtype": "datefilter", "bite": "Data filtered on Year for 2019", "type": "text", "id": "text0000"}, {"bite": "<span class=\"hbheader\">Value</span>: <span class=\"hbvalue\">10489</span>", "priority": 8, "subtype": "topline figure", "uniqueID": "text0017/#indicator+num+value/3/timefilter", "type": "text", "id": "text0017"}, {"priority": 10, "subtype": "datefilter", "bite": "Data filtered on Year for 2019", "type": "text", "id": "text0000"}, {"bite": "<span class=\"hbheader\">Value</span>: <span class=\"hbvalue\">384756.2999446842</span>", "priority": 8, "subtype": "topline figure", "uniqueID": "text0017/#indicator+num+value/3", "type": "text", "id": "text0017"}]}}, "hxl": 1}]}