{"tags": ["facilities and infrastructure", "hxl", "indicators", "Djibouti"], "downloads": 86, "title": "Djibouti - Infrastructure", "hxl": 1, "org": "World Bank Group", "id": "f2d6a470-6be2-4563-ac2f-7e68da940beb", "resources": [{"link": "https://data.humdata.org/dataset/f2d6a470-6be2-4563-ac2f-7e68da940beb/resource/72e4862b-4599-4b9a-bcfc-699385cf4045/download/infrastructure_dji.csv", "update_date": "2021-01-28T06:05:12.700205", "bites": {"maps": {"bites": []}, "charts": {"bites": [{"title": "Top 10 of Value by Indicator Name", "bite": [["Indicator Name", "Value"], ["Revenue from all telecommunication services (current LCU)", 116882893245], ["Annual investment in telecommunications (current LCU)", 24277948206], ["Investment in transport with private participation (current US$)", 576000000], ["Public private partnerships investment in transport (current US$)", 576000000], ["ICT service exports (BoP, current US$)", 204562551.32622716], ["Investment in ICT with private participation (current US$)", 140000000], ["Container port traffic (TEU: 20 foot equivalent units)", 9076664], ["Mobile cellular subscriptions", 3401582], ["Air transport, passengers carried", 1402500], ["Mobile and fixed-line telephone subscribers", 1114197]], "priority": 8, "subtype": "row", "uniqueID": "chart0014/#indicator+name/3/#indicator+num+value/5", "type": "chart", "id": "chart0014"}, {"title": "Top 10 of Value by Indicator Code", "bite": [["Indicator Code", "Value"], ["IT.TEL.REVN.CN", 116882893245], ["IT.TEL.INVS.CN", 24277948206], ["IE.PPI.TRAN.CD", 576000000], ["IE.PPN.TRAN.CD", 576000000], ["BX.GSR.CCIS.CD", 204562551.32622716], ["IE.PPI.ICTI.CD", 140000000], ["IS.SHP.GOOD.TU", 9076664], ["IT.CEL.SETS", 3401582], ["IS.AIR.PSGR", 1402500], ["IT.TEL.TOTL", 1114197]], "priority": 8, "subtype": "row", "uniqueID": "chart0014/#indicator+code/4/#indicator+num+value/5", "type": "chart", "id": "chart0014"}]}, "text": {"bites": [{"bite": "<span class=\"hbheader\">Value</span>: <span class=\"hbvalue\">142673211855.52902</span>", "priority": 8, "subtype": "topline figure", "uniqueID": "text0017/#indicator+num+value/5", "type": "text", "id": "text0017"}]}}, "hxl": 1}, {"link": "https://data.humdata.org/dataset/f2d6a470-6be2-4563-ac2f-7e68da940beb/resource/b148a204-c260-435e-930b-bb741565bd90/download/qc_infrastructure_dji.csv", "update_date": "2021-01-28T06:05:12.700205", "bites": {"maps": {"bites": []}, "charts": {"bites": [{"title": "Value by Indicator Code", "bite": [["Indicator Code", "Value"], ["IS.AIR.DPRT", 44600], ["IS.AIR.PSGR", 1402500], ["IP.IDS.NRCT", 5]], "priority": 8, "subtype": "row", "uniqueID": "chart0007/#indicator+code/2/#indicator+num+value/3", "type": "chart", "id": "chart0007"}]}, "text": {"bites": [{"bite": "<span class=\"hbheader\">Value</span>: <span class=\"hbvalue\">1447105</span>", "priority": 8, "subtype": "topline figure", "uniqueID": "text0017/#indicator+num+value/3", "type": "text", "id": "text0017"}]}}, "hxl": 1}]}